{
  "user1":{
    "name": "Wyoming Townsend",
    "unikey": 17866,
    "password": "/jg4x8EapAbdlWVm4XNg1Q=="
  },
  "user2":{
    "name": "Nola Espinoza",
    "unikey": 17483,
    "password": "E7W/6W8+L+QRyfZvSlgq3w=="
  },
  "user3":{
    "name": "Shay Merritt",
    "unikey": 27037,
    "password": "vRKi98FG5MUZGxL8mic59Q=="
  },
  "user4":{
    "name": "Alfreda Calhoun",
    "unikey": 27846,
    "password": "549UOLSLOby96mG3NnlEnQ=="
  },
  "user5":{
    "name": "Lara Castaneda",
    "unikey": 15133,
    "password": "Bxc8Vm3teb7Tj/s/ZqD6ew=="
  },
  "user6":{
    "name": "Rhonda Morales",
    "unikey": 30018,
    "password": "/q90QQ4gI/ykWbi0630AjQ=="
  },
  "user7":{
    "name": "Jada Leonard",
    "unikey": 26873,
    "password": "vZopFvDgVKk2Gpipe4213A=="
  },
  "user8":{
    "name": "Doris Perry",
    "unikey": 41192,
    "password": "TN9aJdRnO/xFRsp4QwcfZQ=="
  },
  "user9":{
    "name": "Jenette Mcintosh",
    "unikey": 49081,
    "password": "0uFubvUqRbdGjx2la7oZUw=="
  },
  "user10":{
    "name": "Fredericka Fleming",
    "unikey": 36492,
    "password": "/q90QQ4gI/ykWbi0630AjQ=="
  },
  "user11":{
    "name": "Oprah Wilkins",
    "unikey": 20071,
    "password": "Wj49RalG5SziJEcsXbi2pg=="
  },
  "user12":{
    "name": "Jillian Klein",
    "unikey": 13160,
    "password": "4gdUdClJg+AT7k3SIBx6cw=="
  },
  "user13":{
    "name": "Joy Welch",
    "unikey": 13386,
    "password": "YJfA1YJDvgPwOD1mrMX1Dg=="
  },
  "user14":{
    "name": "Oren Peck",
    "unikey": 36037,
    "password": "wREjRH2K/JS+Mve553Qc4Q=="
  },
  "user15":{
    "name": "Lydia Booker",
    "unikey": 31961,
    "password": "U2Jh1U7BsHYmJX7ZiI8PuQ=="
  },
  "user16":{
    "name": "Barclay Flowers",
    "unikey": 16367,
    "password": "F3VEqnl69vMi+Mql6A5/JA=="
  },
  "user17":{
    "name": "Roth Vincent",
    "unikey": 17335,
    "password": "h9Tut97HaGQQdI0XTA4KEQ=="
  },
  "user18":{
    "name": "Ashely Barron",
    "unikey": 17040,
    "password": "h9Tut97HaGQQdI0XTA4KEQ=="
  },
  "user19":{
    "name": "Acton Pena",
    "unikey": 15320,
    "password": "0uFubvUqRbdGjx2la7oZUw=="
  },
  "user20":{
    "name": "Fay Simpson",
    "unikey": 49612,
    "password": "u5jU6cKBsXXqhMUXtZMI6g=="
  },
  "user21":{
    "name": "Jennifer Morales",
    "unikey": 12306,
    "password": "mFErpUteW5+WcWHon1mBgA=="
  },
  "user22":{
    "name": "Kevyn Everett",
    "unikey": 44224,
    "password": "YCKzXfR2WGxUIJxHutlV0g=="
  },
  "user23":{
    "name": "Devin Craft",
    "unikey": 36618,
    "password": "znAcxMq9716subn+JvfKXQ=="
  },
  "user24":{
    "name": "Madison Mcdaniel",
    "unikey": 44011,
    "password": "H65Cftn7AuroUKmzxtGllw=="
  },
  "user25":{
    "name": "Phyllis Moon",
    "unikey": 48288,
    "password": "sOX/MiTvD/A9+sxu516ZGw=="
  },
  "user26":{
    "name": "Nicholas Ellis",
    "unikey": 22450,
    "password": "RhWAVB6SFVdmvunZ6PZy6g=="
  },
  "user27":{
    "name": "Noah Peck",
    "unikey": 25560,
    "password": "Bxc8Vm3teb7Tj/s/ZqD6ew=="
  }
}